decor8ai/__init__.py
decor8ai/client.py
decor8ai/constants.py
decor8ai-0.34.dist-info/METADATA
decor8ai-0.34.dist-info/WHEEL
decor8ai-0.34.dist-info/RECORD
