Metadata-Version: 2.1
Name: decor8ai
Version: 0.34
Summary: Decor8 AI SDK for virtual staging, interior design generation, landscaping, remodeling, wall/cabinet color changes, sky replacement, and sketch-to-3D rendering.
Home-page: https://www.decor8.ai
License: MIT
Keywords: decor8ai,virtual-staging,interior-design,ai,real-estate,landscaping,remodeling,3d-render
Author: Akhilesh Joshi
Author-email: akhilesh@immex.tech
Requires-Python: >=3.10,<4.0
Classifier: Development Status :: 4 - Beta
Classifier: Intended Audience :: Developers
Classifier: License :: OSI Approved :: MIT License
Classifier: Programming Language :: Python :: 3
Classifier: Programming Language :: Python :: 3.10
Classifier: Programming Language :: Python :: 3.11
Classifier: Programming Language :: Python :: 3.12
Classifier: Programming Language :: Python :: 3.13
Requires-Dist: requests (>=2.31.0,<3.0.0)
Project-URL: Repository, https://github.com/immex-tech/decor8ai-sdk
